ogdf_python/__init__.py
ogdf_python/__main__.py
ogdf_python/doxygen.json
ogdf_python/doxygen.py
ogdf_python/info.py
ogdf_python/jupyter.py
ogdf_python/loader.py
ogdf_python/utils.py
ogdf_python/matplotlib/__init__.py
ogdf_python/matplotlib/gui.py
ogdf_python/matplotlib/rendering.h
ogdf_python/matplotlib/util.py
ogdf_python/matplotlib/widget.py
ogdf_python/pythonize/__init__.py
ogdf_python/pythonize/container.py
ogdf_python/pythonize/graph_attributes.py
ogdf_python/pythonize/render.py
ogdf_python/pythonize/string.py
ogdf_python-0.3.4.dist-info/METADATA
ogdf_python-0.3.4.dist-info/WHEEL
ogdf_python-0.3.4.dist-info/RECORD
