Metadata-Version: 2.4
Name: ogdf-python
Version: 0.3.4
Summary: Automagic Python Bindings for the Open Graph Drawing Framework written in C++
Author-email: "Simon D. Fink" <finksim@fim.uni-passau.de>
License-Expression: Apache-2.0
Keywords: algorithm,drawing,graph,network,ogdf
Classifier: Development Status :: 3 - Alpha
Classifier: Intended Audience :: Developers
Classifier: Intended Audience :: Science/Research
Classifier: License :: OSI Approved :: Apache Software License
Classifier: Operating System :: Unix
Classifier: Programming Language :: C++
Classifier: Programming Language :: Python
Classifier: Programming Language :: Python :: 3
Classifier: Programming Language :: Python :: 3 :: Only
Classifier: Programming Language :: Python :: 3.7
Classifier: Programming Language :: Python :: 3.8
Classifier: Programming Language :: Python :: 3.9
Classifier: Programming Language :: Python :: 3.10
Classifier: Programming Language :: Python :: 3.11
Classifier: Topic :: Scientific/Engineering :: Information Analysis
Classifier: Topic :: Scientific/Engineering :: Mathematics
Classifier: Topic :: Scientific/Engineering :: Visualization
Classifier: Topic :: Software Development :: Libraries :: Python Modules
Requires-Python: >=3.7
Requires-Dist: cppyy
Requires-Dist: importlib-resources>=1
Provides-Extra: quickstart
Requires-Dist: ipympl; extra == 'quickstart'
Requires-Dist: jupyterlab; extra == 'quickstart'
Requires-Dist: matplotlib; extra == 'quickstart'
Requires-Dist: ogdf-wheel; extra == 'quickstart'
